README.md
setup.cfg
setup.py
creache.egg-info/PKG-INFO
creache.egg-info/SOURCES.txt
creache.egg-info/dependency_links.txt
creache.egg-info/not-zip-safe
creache.egg-info/requires.txt
creache.egg-info/top_level.txt
src/cli/__init__.py
src/cli/cli.py
src/creache/__init__.py
src/creache/creache.py
src/incrementer/__init__.py
src/incrementer/inc.py