Metadata-Version: 2.1
Name: creache
Version: 1.4000000000000003
Summary: A tool that looks to convert structs to class entities in swift
Home-page: https://github.com/Eyesofbanquo/Creache
Author: Markim Shaw
Author-email: ms79723@gmail.com
License: MIT
Platform: UNKNOWN
Classifier: Development Status :: 3 - Alpha
Classifier: Intended Audience :: Developers
Classifier: Topic :: Software Development :: Build Tools
Classifier: License :: OSI Approved :: MIT License
Classifier: Programming Language :: Python :: 3
Classifier: Programming Language :: Python :: 3.4
Classifier: Programming Language :: Python :: 3.5
Classifier: Programming Language :: Python :: 3.6
